automate.py
main.py
arguments/__init__.py
arguments/arguments.py
token_analyser/__init__.py
token_analyser/token_analyser.py
token_generator/__init__.py
token_generator/token_generator.py
Compilateur_canAda_Zhou_Lo_Morel_Ungaro-0.1.dist-info/METADATA
Compilateur_canAda_Zhou_Lo_Morel_Ungaro-0.1.dist-info/WHEEL
Compilateur_canAda_Zhou_Lo_Morel_Ungaro-0.1.dist-info/entry_points.txt
Compilateur_canAda_Zhou_Lo_Morel_Ungaro-0.1.dist-info/top_level.txt
Compilateur_canAda_Zhou_Lo_Morel_Ungaro-0.1.dist-info/RECORD
