Metadata-Version: 2.1
Name: Compilateur-canAda-Zhou-Lo-Morel-Ungaro
Version: 0.1
Summary: Compilateur canAda
